tinypipeline/__init__.py
tinypipeline/pipeline.py
tinypipeline/step.py
tinypipeline-0.3.0.dist-info/LICENSE
tinypipeline-0.3.0.dist-info/METADATA
tinypipeline-0.3.0.dist-info/WHEEL
tinypipeline-0.3.0.dist-info/top_level.txt
tinypipeline-0.3.0.dist-info/RECORD
