Metadata-Version: 2.1
Name: tinypipeline
Version: 0.3.0
Summary: A tiny mlops library for building machine learning pipelines on your local machine.
Author-email: Freddie Vargus <fjv41995@gmail.com>
License: MIT
Keywords: mlops,machine learning,pipelines
Classifier: Programming Language :: Python :: 3
Classifier: License :: OSI Approved :: MIT License
Requires-Python: >=3.9
License-File: LICENSE
